regit/__init__.py
regit/regit.py
regit-0.0.2.dist-info/LICENSE
regit-0.0.2.dist-info/METADATA
regit-0.0.2.dist-info/WHEEL
regit-0.0.2.dist-info/entry_points.txt
regit-0.0.2.dist-info/top_level.txt
regit-0.0.2.dist-info/RECORD
