Metadata-Version: 2.1
Name: regit
Version: 0.0.2
Summary: regit: a dpe branch dependency manager
Home-page: https://github.com/kaspar030/regit
Author: Kaspar Schleiser
Author-email: kaspar@schleiser.de
License: GPLv3
Keywords: git plugin
Platform: UNKNOWN
Classifier: Development Status :: 3 - Alpha
Classifier: Intended Audience :: Developers
Classifier: Topic :: Software Development :: Version Control :: Git
Classifier: License :: OSI Approved :: GNU General Public License v3 (GPLv3)
Classifier: Programming Language :: Python :: 3.4
Classifier: Programming Language :: Python :: 3.5
Classifier: Programming Language :: Python :: 3.6
Classifier: Programming Language :: Python :: 3.7
